CHANGELOG.txt
LICENSE.txt
MANIFEST.in
README.rst
setup.py
docs/Makefile
docs/conf.py
docs/gyroid.rst
docs/index.rst
docs/make.bat
docs/_build/doctrees/environment.pickle
docs/_build/doctrees/gyroid.doctree
docs/_build/doctrees/index.doctree
docs/_build/html/.buildinfo
docs/_build/html/genindex.html
docs/_build/html/gyroid-doc.zip
docs/_build/html/gyroid.html
docs/_build/html/index.html
docs/_build/html/objects.inv
docs/_build/html/py-modindex.html
docs/_build/html/search.html
docs/_build/html/searchindex.js
docs/_build/html/_modules/index.html
docs/_build/html/_modules/gyroid/basis.html
docs/_build/html/_modules/gyroid/grid.html
docs/_build/html/_modules/gyroid/group.html
docs/_build/html/_modules/gyroid/space_group.html
docs/_build/html/_modules/gyroid/symmetry.html
docs/_build/html/_modules/gyroid/unitcell.html
docs/_build/html/_modules/gyroid/util.html
docs/_build/html/_sources/gyroid.txt
docs/_build/html/_sources/index.txt
docs/_build/html/_static/ajax-loader.gif
docs/_build/html/_static/basic.css
docs/_build/html/_static/comment-bright.png
docs/_build/html/_static/comment-close.png
docs/_build/html/_static/comment.png
docs/_build/html/_static/doctools.js
docs/_build/html/_static/down-pressed.png
docs/_build/html/_static/down.png
docs/_build/html/_static/file.png
docs/_build/html/_static/flasky.css
docs/_build/html/_static/jquery.js
docs/_build/html/_static/minus.png
docs/_build/html/_static/plus.png
docs/_build/html/_static/pygments.css
docs/_build/html/_static/searchtools.js
docs/_build/html/_static/small_flask.css
docs/_build/html/_static/underscore.js
docs/_build/html/_static/up-pressed.png
docs/_build/html/_static/up.png
docs/_build/html/_static/websupport.js
docs/_themes/.gitignore
docs/_themes/LICENSE
docs/_themes/README
docs/_themes/flask_theme_support.py
docs/_themes/flask_theme_support.pyc
docs/_themes/flask/layout.html
docs/_themes/flask/relations.html
docs/_themes/flask/theme.conf
docs/_themes/flask/static/flasky.css_t
gyroid.egg-info/PKG-INFO
gyroid.egg-info/SOURCES.txt
gyroid.egg-info/dependency_links.txt
gyroid.egg-info/not-zip-safe
gyroid.egg-info/requires.txt
gyroid.egg-info/top_level.txt
