Metadata-Version: 1.0
Name: gyroid
Version: 0.4
Summary: A symmetry adapted basis function (SABF) generator.
Home-page: https://bitbucket.org/liuyxpp/gyroid
Author: Yi-Xin Liu
Author-email: liuyxpp@gmail.com
License: BSD
Platform: UNKNOWN
Classifier: Development Status :: 4 - Beta
Classifier: Environment :: Console
Classifier: Environment :: X11 Applications
Classifier: Intended Audience :: Science/Research
Classifier: Intended Audience :: Developers
Classifier: Intended Audience :: Education
Classifier: License :: OSI Approved :: BSD License
Classifier: Operating System :: POSIX :: Linux
Classifier: Programming Language :: Python
Classifier: Topic :: Scientific/Engineering
Classifier: Topic :: Education
Classifier: Topic :: Multimedia :: Graphics
